Chessnut/__init__.py
Chessnut/board.py
Chessnut/game.py
Chessnut/moves.py
Chessnut4jschultz38-0.3.10.dist-info/METADATA
Chessnut4jschultz38-0.3.10.dist-info/WHEEL
Chessnut4jschultz38-0.3.10.dist-info/top_level.txt
Chessnut4jschultz38-0.3.10.dist-info/RECORD
